niftiwidget/__init__.py
niftiwidget/main.py
niftiwidget/utils.py
niftiwidget-0.0.1.dist-info/LICENSE
niftiwidget-0.0.1.dist-info/METADATA
niftiwidget-0.0.1.dist-info/WHEEL
niftiwidget-0.0.1.dist-info/RECORD
