Metadata-Version: 2.1
Name: niftiwidget
Version: 0.0.1
Summary: View volumetric images in Jupyter 🧠
Home-page: https://github.com/codingfisch/niftiwidget
License: MIT
Author: codingfisch
Author-email: l_fisc17@wwu.de
Requires-Python: >=3.9,<4.0
Classifier: Intended Audience :: Science/Research
Classifier: License :: OSI Approved :: MIT License
Classifier: Operating System :: OS Independent
Classifier: Programming Language :: Python :: 3
Classifier: Programming Language :: Python :: 3.9
Classifier: Programming Language :: Python :: 3.10
Classifier: Programming Language :: Python :: 3.11
Classifier: Programming Language :: Python :: 3.12
Classifier: Programming Language :: Python :: 3.13
Requires-Dist: fpng_py
Requires-Dist: niftiview
Project-URL: Repository, https://github.com/codingfisch/niftiwidget
